sentry_dingding/__init__.py
sentry_dingding/forms.py
sentry_dingding/plugin.py
sentry_dingding_vibranium-1.0.1.dist-info/METADATA
sentry_dingding_vibranium-1.0.1.dist-info/WHEEL
sentry_dingding_vibranium-1.0.1.dist-info/entry_points.txt
sentry_dingding_vibranium-1.0.1.dist-info/top_level.txt
sentry_dingding_vibranium-1.0.1.dist-info/RECORD
