Metadata-Version: 2.1
Name: sentry-dingding-vibranium
Version: 1.0.1
Summary: A Sentry extension which send errors stats to DingDing
Home-page: https://github.com/stevenQiang/sentry-dingding-vibranium
Author: steven
Author-email: qianggao7@gmail.com
License: MIT
Keywords: sentry dingding
Platform: UNKNOWN
Classifier: Programming Language :: Python :: 2.7
Classifier: License :: OSI Approved :: MIT License
Requires-Dist: sentry (>=9.0.0)
Requires-Dist: requests
